{"nodes": [{"id": "home_lviffy_projects_casper_contract_src_cep18_rs", "label": "cep18.rs", "file_type": "code", "source_file": "contract/src/cep18.rs", "source_location": "L1"}, {"id": "src_cep18_burn", "label": "Burn", "file_type": "code", "source_file": "contract/src/cep18.rs", "source_location": "L15"}, {"id": "address", "label": "Address", "file_type": "code", "source_file": "", "source_location": ""}, {"id": "u256", "label": "U256", "file_type": "code", "source_file": "", "source_location": ""}, {"id": "src_cep18_cep18token", "label": "Cep18Token", "file_type": "code", "source_file": "contract/src/cep18.rs", "source_location": "L21"}, {"id": "var", "label": "Var", "file_type": "code", "source_file": "", "source_location": ""}, {"id": "string", "label": "String", "file_type": "code", "source_file": "", "source_location": ""}, {"id": "mapping", "label": "Mapping", "file_type": "code", "source_file": "", "source_location": ""}, {"id": "src_cep18_cep18token_init", "label": ".init()", "file_type": "code", "source_file": "contract/src/cep18.rs", "source_location": "L32"}, {"id": "src_cep18_cep18token_transfer", "label": ".transfer()", "file_type": "code", "source_file": "contract/src/cep18.rs", "source_location": "L47"}, {"id": "src_cep18_cep18token_approve", "label": ".approve()", "file_type": "code", "source_file": "contract/src/cep18.rs", "source_location": "L52"}, {"id": "src_cep18_cep18token_transfer_from", "label": ".transfer_from()", "file_type": "code", "source_file": "contract/src/cep18.rs", "source_location": "L57"}, {"id": "src_cep18_cep18token_burn", "label": ".burn()", "file_type": "code", "source_file": "contract/src/cep18.rs", "source_location": "L68"}, {"id": "src_cep18_cep18token_balance_of", "label": ".balance_of()", "file_type": "code", "source_file": "contract/src/cep18.rs", "source_location": "L83"}, {"id": "src_cep18_cep18token_allowance", "label": ".allowance()", "file_type": "code", "source_file": "contract/src/cep18.rs", "source_location": "L87"}, {"id": "src_cep18_cep18token_total_supply", "label": ".total_supply()", "file_type": "code", "source_file": "contract/src/cep18.rs", "source_location": "L91"}, {"id": "src_cep18_cep18token_move_tokens", "label": ".move_tokens()", "file_type": "code", "source_file": "contract/src/cep18.rs", "source_location": "L97"}, {"id": "src_cep18_error", "label": "Error", "file_type": "code", "source_file": "contract/src/cep18.rs", "source_location": "L109"}, {"id": "src_cep18_deploy_with_supply", "label": "deploy_with_supply()", "file_type": "code", "source_file": "contract/src/cep18.rs", "source_location": "L124"}, {"id": "hostenv", "label": "HostEnv", "file_type": "code", "source_file": "", "source_location": ""}, {"id": "cep18tokenhostref", "label": "Cep18TokenHostRef", "file_type": "code", "source_file": "", "source_location": ""}, {"id": "src_cep18_test_cep18_initial_supply_assigned_to_deployer", "label": "test_cep18_initial_supply_assigned_to_deployer()", "file_type": "code", "source_file": "contract/src/cep18.rs", "source_location": "L139"}, {"id": "src_cep18_test_cep18_transfer_moves_balance", "label": "test_cep18_transfer_moves_balance()", "file_type": "code", "source_file": "contract/src/cep18.rs", "source_location": "L147"}, {"id": "src_cep18_test_cep18_transfer_reverts_on_insufficient_balance", "label": "test_cep18_transfer_reverts_on_insufficient_balance()", "file_type": "code", "source_file": "contract/src/cep18.rs", "source_location": "L159"}, {"id": "src_cep18_test_cep18_approve_and_transfer_from", "label": "test_cep18_approve_and_transfer_from()", "file_type": "code", "source_file": "contract/src/cep18.rs", "source_location": "L167"}, {"id": "src_cep18_test_cep18_transfer_from_reverts_on_insufficient_allowance", "label": "test_cep18_transfer_from_reverts_on_insufficient_allowance()", "file_type": "code", "source_file": "contract/src/cep18.rs", "source_location": "L184"}, {"id": "src_cep18_test_cep18_burn_reduces_balance_and_total_supply", "label": "test_cep18_burn_reduces_balance_and_total_supply()", "file_type": "code", "source_file": "contract/src/cep18.rs", "source_location": "L196"}, {"id": "src_cep18_test_cep18_burn_reverts_on_insufficient_balance", "label": "test_cep18_burn_reverts_on_insufficient_balance()", "file_type": "code", "source_file": "contract/src/cep18.rs", "source_location": "L207"}, {"id": "src_cep18_test_cep18_burn_reverts_when_caller_has_no_balance", "label": "test_cep18_burn_reverts_when_caller_has_no_balance()", "file_type": "code", "source_file": "contract/src/cep18.rs", "source_location": "L215"}, {"id": "src_cep18_test_cep18_burn_only_affects_caller", "label": "test_cep18_burn_only_affects_caller()", "file_type": "code", "source_file": "contract/src/cep18.rs", "source_location": "L223"}, {"id": "src_cep18_test_cep18_burn_emits_event", "label": "test_cep18_burn_emits_event()", "file_type": "code", "source_file": "contract/src/cep18.rs", "source_location": "L237"}, {"id": "src_cep18_test_cep18_burn_full_balance_zeros_total_supply", "label": "test_cep18_burn_full_balance_zeros_total_supply()", "file_type": "code", "source_file": "contract/src/cep18.rs", "source_location": "L249"}], "edges": [{"source": "home_lviffy_projects_casper_contract_src_cep18_rs", "target": "event", "relation": "imports_from", "confidence": "EXTRACTED", "source_file": "contract/src/cep18.rs", "source_location": "L10", "weight": 1.0, "context": "import"}, {"source": "home_lviffy_projects_casper_contract_src_cep18_rs", "target": "prelude", "relation": "imports_from", "confidence": "EXTRACTED", "source_file": "contract/src/cep18.rs", "source_location": "L11", "weight": 1.0, "context": "import"}, {"source": "home_lviffy_projects_casper_contract_src_cep18_rs", "target": "u256", "relation": "imports_from", "confidence": "EXTRACTED", "source_file": "contract/src/cep18.rs", "source_location": "L12", "weight": 1.0, "context": "import"}, {"source": "home_lviffy_projects_casper_contract_src_cep18_rs", "target": "src_cep18_burn", "relation": "contains", "confidence": "EXTRACTED", "source_file": "contract/src/cep18.rs", "source_location": "L15", "weight": 1.0}, {"source": "src_cep18_burn", "target": "address", "relation": "references", "confidence": "EXTRACTED", "source_file": "contract/src/cep18.rs", "source_location": "L16", "weight": 1.0, "context": "field"}, {"source": "src_cep18_burn", "target": "u256", "relation": "references", "confidence": "EXTRACTED", "source_file": "contract/src/cep18.rs", "source_location": "L17", "weight": 1.0, "context": "field"}, {"source": "home_lviffy_projects_casper_contract_src_cep18_rs", "target": "src_cep18_cep18token", "relation": "contains", "confidence": "EXTRACTED", "source_file": "contract/src/cep18.rs", "source_location": "L21", "weight": 1.0}, {"source": "src_cep18_cep18token", "target": "var", "relation": "references", "confidence": "EXTRACTED", "source_file": "contract/src/cep18.rs", "source_location": "L22", "weight": 1.0, "context": "field"}, {"source": "src_cep18_cep18token", "target": "string", "relation": "references", "confidence": "EXTRACTED", "source_file": "contract/src/cep18.rs", "source_location": "L22", "weight": 1.0, "context": "generic_arg"}, {"source": "src_cep18_cep18token", "target": "var", "relation": "references", "confidence": "EXTRACTED", "source_file": "contract/src/cep18.rs", "source_location": "L23", "weight": 1.0, "context": "field"}, {"source": "src_cep18_cep18token", "target": "string", "relation": "references", "confidence": "EXTRACTED", "source_file": "contract/src/cep18.rs", "source_location": "L23", "weight": 1.0, "context": "generic_arg"}, {"source": "src_cep18_cep18token", "target": "var", "relation": "references", "confidence": "EXTRACTED", "source_file": "contract/src/cep18.rs", "source_location": "L24", "weight": 1.0, "context": "field"}, {"source": "src_cep18_cep18token", "target": "var", "relation": "references", "confidence": "EXTRACTED", "source_file": "contract/src/cep18.rs", "source_location": "L25", "weight": 1.0, "context": "field"}, {"source": "src_cep18_cep18token", "target": "u256", "relation": "references", "confidence": "EXTRACTED", "source_file": "contract/src/cep18.rs", "source_location": "L25", "weight": 1.0, "context": "generic_arg"}, {"source": "src_cep18_cep18token", "target": "mapping", "relation": "references", "confidence": "EXTRACTED", "source_file": "contract/src/cep18.rs", "source_location": "L26", "weight": 1.0, "context": "field"}, {"source": "src_cep18_cep18token", "target": "address", "relation": "references", "confidence": "EXTRACTED", "source_file": "contract/src/cep18.rs", "source_location": "L26", "weight": 1.0, "context": "generic_arg"}, {"source": "src_cep18_cep18token", "target": "u256", "relation": "references", "confidence": "EXTRACTED", "source_file": "contract/src/cep18.rs", "source_location": "L26", "weight": 1.0, "context": "generic_arg"}, {"source": "src_cep18_cep18token", "target": "mapping", "relation": "references", "confidence": "EXTRACTED", "source_file": "contract/src/cep18.rs", "source_location": "L27", "weight": 1.0, "context": "field"}, {"source": "src_cep18_cep18token", "target": "address", "relation": "references", "confidence": "EXTRACTED", "source_file": "contract/src/cep18.rs", "source_location": "L27", "weight": 1.0, "context": "generic_arg"}, {"source": "src_cep18_cep18token", "target": "address", "relation": "references", "confidence": "EXTRACTED", "source_file": "contract/src/cep18.rs", "source_location": "L27", "weight": 1.0, "context": "generic_arg"}, {"source": "src_cep18_cep18token", "target": "u256", "relation": "references", "confidence": "EXTRACTED", "source_file": "contract/src/cep18.rs", "source_location": "L27", "weight": 1.0, "context": "generic_arg"}, {"source": "src_cep18_cep18token", "target": "src_cep18_cep18token_init", "relation": "method", "confidence": "EXTRACTED", "source_file": "contract/src/cep18.rs", "source_location": "L32", "weight": 1.0}, {"source": "src_cep18_cep18token_init", "target": "string", "relation": "references", "confidence": "EXTRACTED", "source_file": "contract/src/cep18.rs", "source_location": "L32", "weight": 1.0, "context": "parameter_type"}, {"source": "src_cep18_cep18token_init", "target": "string", "relation": "references", "confidence": "EXTRACTED", "source_file": "contract/src/cep18.rs", "source_location": "L32", "weight": 1.0, "context": "parameter_type"}, {"source": "src_cep18_cep18token_init", "target": "u256", "relation": "references", "confidence": "EXTRACTED", "source_file": "contract/src/cep18.rs", "source_location": "L32", "weight": 1.0, "context": "parameter_type"}, {"source": "src_cep18_cep18token", "target": "src_cep18_cep18token_transfer", "relation": "method", "confidence": "EXTRACTED", "source_file": "contract/src/cep18.rs", "source_location": "L47", "weight": 1.0}, {"source": "src_cep18_cep18token_transfer", "target": "address", "relation": "references", "confidence": "EXTRACTED", "source_file": "contract/src/cep18.rs", "source_location": "L47", "weight": 1.0, "context": "parameter_type"}, {"source": "src_cep18_cep18token_transfer", "target": "u256", "relation": "references", "confidence": "EXTRACTED", "source_file": "contract/src/cep18.rs", "source_location": "L47", "weight": 1.0, "context": "parameter_type"}, {"source": "src_cep18_cep18token", "target": "src_cep18_cep18token_approve", "relation": "method", "confidence": "EXTRACTED", "source_file": "contract/src/cep18.rs", "source_location": "L52", "weight": 1.0}, {"source": "src_cep18_cep18token_approve", "target": "address", "relation": "references", "confidence": "EXTRACTED", "source_file": "contract/src/cep18.rs", "source_location": "L52", "weight": 1.0, "context": "parameter_type"}, {"source": "src_cep18_cep18token_approve", "target": "u256", "relation": "references", "confidence": "EXTRACTED", "source_file": "contract/src/cep18.rs", "source_location": "L52", "weight": 1.0, "context": "parameter_type"}, {"source": "src_cep18_cep18token", "target": "src_cep18_cep18token_transfer_from", "relation": "method", "confidence": "EXTRACTED", "source_file": "contract/src/cep18.rs", "source_location": "L57", "weight": 1.0}, {"source": "src_cep18_cep18token_transfer_from", "target": "address", "relation": "references", "confidence": "EXTRACTED", "source_file": "contract/src/cep18.rs", "source_location": "L57", "weight": 1.0, "context": "parameter_type"}, {"source": "src_cep18_cep18token_transfer_from", "target": "address", "relation": "references", "confidence": "EXTRACTED", "source_file": "contract/src/cep18.rs", "source_location": "L57", "weight": 1.0, "context": "parameter_type"}, {"source": "src_cep18_cep18token_transfer_from", "target": "u256", "relation": "references", "confidence": "EXTRACTED", "source_file": "contract/src/cep18.rs", "source_location": "L57", "weight": 1.0, "context": "parameter_type"}, {"source": "src_cep18_cep18token", "target": "src_cep18_cep18token_burn", "relation": "method", "confidence": "EXTRACTED", "source_file": "contract/src/cep18.rs", "source_location": "L68", "weight": 1.0}, {"source": "src_cep18_cep18token_burn", "target": "u256", "relation": "references", "confidence": "EXTRACTED", "source_file": "contract/src/cep18.rs", "source_location": "L68", "weight": 1.0, "context": "parameter_type"}, {"source": "src_cep18_cep18token", "target": "src_cep18_cep18token_balance_of", "relation": "method", "confidence": "EXTRACTED", "source_file": "contract/src/cep18.rs", "source_location": "L83", "weight": 1.0}, {"source": "src_cep18_cep18token_balance_of", "target": "address", "relation": "references", "confidence": "EXTRACTED", "source_file": "contract/src/cep18.rs", "source_location": "L83", "weight": 1.0, "context": "parameter_type"}, {"source": "src_cep18_cep18token_balance_of", "target": "u256", "relation": "references", "confidence": "EXTRACTED", "source_file": "contract/src/cep18.rs", "source_location": "L83", "weight": 1.0, "context": "return_type"}, {"source": "src_cep18_cep18token", "target": "src_cep18_cep18token_allowance", "relation": "method", "confidence": "EXTRACTED", "source_file": "contract/src/cep18.rs", "source_location": "L87", "weight": 1.0}, {"source": "src_cep18_cep18token_allowance", "target": "address", "relation": "references", "confidence": "EXTRACTED", "source_file": "contract/src/cep18.rs", "source_location": "L87", "weight": 1.0, "context": "parameter_type"}, {"source": "src_cep18_cep18token_allowance", "target": "address", "relation": "references", "confidence": "EXTRACTED", "source_file": "contract/src/cep18.rs", "source_location": "L87", "weight": 1.0, "context": "parameter_type"}, {"source": "src_cep18_cep18token_allowance", "target": "u256", "relation": "references", "confidence": "EXTRACTED", "source_file": "contract/src/cep18.rs", "source_location": "L87", "weight": 1.0, "context": "return_type"}, {"source": "src_cep18_cep18token", "target": "src_cep18_cep18token_total_supply", "relation": "method", "confidence": "EXTRACTED", "source_file": "contract/src/cep18.rs", "source_location": "L91", "weight": 1.0}, {"source": "src_cep18_cep18token_total_supply", "target": "u256", "relation": "references", "confidence": "EXTRACTED", "source_file": "contract/src/cep18.rs", "source_location": "L91", "weight": 1.0, "context": "return_type"}, {"source": "src_cep18_cep18token", "target": "src_cep18_cep18token_move_tokens", "relation": "method", "confidence": "EXTRACTED", "source_file": "contract/src/cep18.rs", "source_location": "L97", "weight": 1.0}, {"source": "src_cep18_cep18token_move_tokens", "target": "address", "relation": "references", "confidence": "EXTRACTED", "source_file": "contract/src/cep18.rs", "source_location": "L97", "weight": 1.0, "context": "parameter_type"}, {"source": "src_cep18_cep18token_move_tokens", "target": "address", "relation": "references", "confidence": "EXTRACTED", "source_file": "contract/src/cep18.rs", "source_location": "L97", "weight": 1.0, "context": "parameter_type"}, {"source": "src_cep18_cep18token_move_tokens", "target": "u256", "relation": "references", "confidence": "EXTRACTED", "source_file": "contract/src/cep18.rs", "source_location": "L97", "weight": 1.0, "context": "parameter_type"}, {"source": "home_lviffy_projects_casper_contract_src_cep18_rs", "target": "src_cep18_error", "relation": "contains", "confidence": "EXTRACTED", "source_file": "contract/src/cep18.rs", "source_location": "L109", "weight": 1.0}, {"source": "home_lviffy_projects_casper_contract_src_cep18_rs", "target": "super", "relation": "imports_from", "confidence": "EXTRACTED", "source_file": "contract/src/cep18.rs", "source_location": "L116", "weight": 1.0, "context": "import"}, {"source": "home_lviffy_projects_casper_contract_src_cep18_rs", "target": "eventinstance", "relation": "imports_from", "confidence": "EXTRACTED", "source_file": "contract/src/cep18.rs", "source_location": "L117", "weight": 1.0, "context": "import"}, {"source": "home_lviffy_projects_casper_contract_src_cep18_rs", "target": "u256", "relation": "imports_from", "confidence": "EXTRACTED", "source_file": "contract/src/cep18.rs", "source_location": "L118", "weight": 1.0, "context": "import"}, {"source": "home_lviffy_projects_casper_contract_src_cep18_rs", "target": "deployer", "relation": "imports_from", "confidence": "EXTRACTED", "source_file": "contract/src/cep18.rs", "source_location": "L119", "weight": 1.0, "context": "import"}, {"source": "home_lviffy_projects_casper_contract_src_cep18_rs", "target": "odracontract", "relation": "imports_from", "confidence": "EXTRACTED", "source_file": "contract/src/cep18.rs", "source_location": "L120", "weight": 1.0, "context": "import"}, {"source": "home_lviffy_projects_casper_contract_src_cep18_rs", "target": "src_cep18_deploy_with_supply", "relation": "contains", "confidence": "EXTRACTED", "source_file": "contract/src/cep18.rs", "source_location": "L124", "weight": 1.0}, {"source": "src_cep18_deploy_with_supply", "target": "hostenv", "relation": "references", "confidence": "EXTRACTED", "source_file": "contract/src/cep18.rs", "source_location": "L124", "weight": 1.0, "context": "return_type"}, {"source": "src_cep18_deploy_with_supply", "target": "cep18tokenhostref", "relation": "references", "confidence": "EXTRACTED", "source_file": "contract/src/cep18.rs", "source_location": "L124", "weight": 1.0, "context": "return_type"}, {"source": "home_lviffy_projects_casper_contract_src_cep18_rs", "target": "src_cep18_test_cep18_initial_supply_assigned_to_deployer", "relation": "contains", "confidence": "EXTRACTED", "source_file": "contract/src/cep18.rs", "source_location": "L139", "weight": 1.0}, {"source": "home_lviffy_projects_casper_contract_src_cep18_rs", "target": "src_cep18_test_cep18_transfer_moves_balance", "relation": "contains", "confidence": "EXTRACTED", "source_file": "contract/src/cep18.rs", "source_location": "L147", "weight": 1.0}, {"source": "home_lviffy_projects_casper_contract_src_cep18_rs", "target": "src_cep18_test_cep18_transfer_reverts_on_insufficient_balance", "relation": "contains", "confidence": "EXTRACTED", "source_file": "contract/src/cep18.rs", "source_location": "L159", "weight": 1.0}, {"source": "home_lviffy_projects_casper_contract_src_cep18_rs", "target": "src_cep18_test_cep18_approve_and_transfer_from", "relation": "contains", "confidence": "EXTRACTED", "source_file": "contract/src/cep18.rs", "source_location": "L167", "weight": 1.0}, {"source": "home_lviffy_projects_casper_contract_src_cep18_rs", "target": "src_cep18_test_cep18_transfer_from_reverts_on_insufficient_allowance", "relation": "contains", "confidence": "EXTRACTED", "source_file": "contract/src/cep18.rs", "source_location": "L184", "weight": 1.0}, {"source": "home_lviffy_projects_casper_contract_src_cep18_rs", "target": "src_cep18_test_cep18_burn_reduces_balance_and_total_supply", "relation": "contains", "confidence": "EXTRACTED", "source_file": "contract/src/cep18.rs", "source_location": "L196", "weight": 1.0}, {"source": "home_lviffy_projects_casper_contract_src_cep18_rs", "target": "src_cep18_test_cep18_burn_reverts_on_insufficient_balance", "relation": "contains", "confidence": "EXTRACTED", "source_file": "contract/src/cep18.rs", "source_location": "L207", "weight": 1.0}, {"source": "home_lviffy_projects_casper_contract_src_cep18_rs", "target": "src_cep18_test_cep18_burn_reverts_when_caller_has_no_balance", "relation": "contains", "confidence": "EXTRACTED", "source_file": "contract/src/cep18.rs", "source_location": "L215", "weight": 1.0}, {"source": "home_lviffy_projects_casper_contract_src_cep18_rs", "target": "src_cep18_test_cep18_burn_only_affects_caller", "relation": "contains", "confidence": "EXTRACTED", "source_file": "contract/src/cep18.rs", "source_location": "L223", "weight": 1.0}, {"source": "home_lviffy_projects_casper_contract_src_cep18_rs", "target": "src_cep18_test_cep18_burn_emits_event", "relation": "contains", "confidence": "EXTRACTED", "source_file": "contract/src/cep18.rs", "source_location": "L237", "weight": 1.0}, {"source": "home_lviffy_projects_casper_contract_src_cep18_rs", "target": "src_cep18_test_cep18_burn_full_balance_zeros_total_supply", "relation": "contains", "confidence": "EXTRACTED", "source_file": "contract/src/cep18.rs", "source_location": "L249", "weight": 1.0}, {"source": "src_cep18_cep18token_transfer", "target": "src_cep18_cep18token_move_tokens", "relation": "calls", "context": "call", "confidence": "EXTRACTED", "source_file": "contract/src/cep18.rs", "source_location": "L49", "weight": 1.0}, {"source": "src_cep18_cep18token_transfer_from", "target": "src_cep18_cep18token_move_tokens", "relation": "calls", "context": "call", "confidence": "EXTRACTED", "source_file": "contract/src/cep18.rs", "source_location": "L64", "weight": 1.0}, {"source": "src_cep18_test_cep18_initial_supply_assigned_to_deployer", "target": "src_cep18_deploy_with_supply", "relation": "calls", "context": "call", "confidence": "EXTRACTED", "source_file": "contract/src/cep18.rs", "source_location": "L140", "weight": 1.0}, {"source": "src_cep18_test_cep18_transfer_moves_balance", "target": "src_cep18_deploy_with_supply", "relation": "calls", "context": "call", "confidence": "EXTRACTED", "source_file": "contract/src/cep18.rs", "source_location": "L148", "weight": 1.0}, {"source": "src_cep18_test_cep18_transfer_moves_balance", "target": "src_cep18_cep18token_transfer", "relation": "calls", "context": "call", "confidence": "EXTRACTED", "source_file": "contract/src/cep18.rs", "source_location": "L152", "weight": 1.0}, {"source": "src_cep18_test_cep18_transfer_reverts_on_insufficient_balance", "target": "src_cep18_deploy_with_supply", "relation": "calls", "context": "call", "confidence": "EXTRACTED", "source_file": "contract/src/cep18.rs", "source_location": "L160", "weight": 1.0}, {"source": "src_cep18_test_cep18_transfer_reverts_on_insufficient_balance", "target": "src_cep18_cep18token_transfer", "relation": "calls", "context": "call", "confidence": "EXTRACTED", "source_file": "contract/src/cep18.rs", "source_location": "L163", "weight": 1.0}, {"source": "src_cep18_test_cep18_approve_and_transfer_from", "target": "src_cep18_deploy_with_supply", "relation": "calls", "context": "call", "confidence": "EXTRACTED", "source_file": "contract/src/cep18.rs", "source_location": "L168", "weight": 1.0}, {"source": "src_cep18_test_cep18_approve_and_transfer_from", "target": "src_cep18_cep18token_approve", "relation": "calls", "context": "call", "confidence": "EXTRACTED", "source_file": "contract/src/cep18.rs", "source_location": "L173", "weight": 1.0}, {"source": "src_cep18_test_cep18_approve_and_transfer_from", "target": "src_cep18_cep18token_transfer_from", "relation": "calls", "context": "call", "confidence": "EXTRACTED", "source_file": "contract/src/cep18.rs", "source_location": "L176", "weight": 1.0}, {"source": "src_cep18_test_cep18_transfer_from_reverts_on_insufficient_allowance", "target": "src_cep18_deploy_with_supply", "relation": "calls", "context": "call", "confidence": "EXTRACTED", "source_file": "contract/src/cep18.rs", "source_location": "L185", "weight": 1.0}, {"source": "src_cep18_test_cep18_transfer_from_reverts_on_insufficient_allowance", "target": "src_cep18_cep18token_approve", "relation": "calls", "context": "call", "confidence": "EXTRACTED", "source_file": "contract/src/cep18.rs", "source_location": "L190", "weight": 1.0}, {"source": "src_cep18_test_cep18_transfer_from_reverts_on_insufficient_allowance", "target": "src_cep18_cep18token_transfer_from", "relation": "calls", "context": "call", "confidence": "EXTRACTED", "source_file": "contract/src/cep18.rs", "source_location": "L192", "weight": 1.0}, {"source": "src_cep18_test_cep18_burn_reduces_balance_and_total_supply", "target": "src_cep18_deploy_with_supply", "relation": "calls", "context": "call", "confidence": "EXTRACTED", "source_file": "contract/src/cep18.rs", "source_location": "L197", "weight": 1.0}, {"source": "src_cep18_test_cep18_burn_reduces_balance_and_total_supply", "target": "src_cep18_cep18token_burn", "relation": "calls", "context": "call", "confidence": "EXTRACTED", "source_file": "contract/src/cep18.rs", "source_location": "L200", "weight": 1.0}, {"source": "src_cep18_test_cep18_burn_reverts_on_insufficient_balance", "target": "src_cep18_deploy_with_supply", "relation": "calls", "context": "call", "confidence": "EXTRACTED", "source_file": "contract/src/cep18.rs", "source_location": "L208", "weight": 1.0}, {"source": "src_cep18_test_cep18_burn_reverts_on_insufficient_balance", "target": "src_cep18_cep18token_burn", "relation": "calls", "context": "call", "confidence": "EXTRACTED", "source_file": "contract/src/cep18.rs", "source_location": "L210", "weight": 1.0}, {"source": "src_cep18_test_cep18_burn_reverts_when_caller_has_no_balance", "target": "src_cep18_deploy_with_supply", "relation": "calls", "context": "call", "confidence": "EXTRACTED", "source_file": "contract/src/cep18.rs", "source_location": "L216", "weight": 1.0}, {"source": "src_cep18_test_cep18_burn_reverts_when_caller_has_no_balance", "target": "src_cep18_cep18token_burn", "relation": "calls", "context": "call", "confidence": "EXTRACTED", "source_file": "contract/src/cep18.rs", "source_location": "L219", "weight": 1.0}, {"source": "src_cep18_test_cep18_burn_only_affects_caller", "target": "src_cep18_deploy_with_supply", "relation": "calls", "context": "call", "confidence": "EXTRACTED", "source_file": "contract/src/cep18.rs", "source_location": "L224", "weight": 1.0}, {"source": "src_cep18_test_cep18_burn_only_affects_caller", "target": "src_cep18_cep18token_transfer", "relation": "calls", "context": "call", "confidence": "EXTRACTED", "source_file": "contract/src/cep18.rs", "source_location": "L228", "weight": 1.0}, {"source": "src_cep18_test_cep18_burn_only_affects_caller", "target": "src_cep18_cep18token_burn", "relation": "calls", "context": "call", "confidence": "EXTRACTED", "source_file": "contract/src/cep18.rs", "source_location": "L230", "weight": 1.0}, {"source": "src_cep18_test_cep18_burn_emits_event", "target": "src_cep18_deploy_with_supply", "relation": "calls", "context": "call", "confidence": "EXTRACTED", "source_file": "contract/src/cep18.rs", "source_location": "L238", "weight": 1.0}, {"source": "src_cep18_test_cep18_burn_emits_event", "target": "src_cep18_cep18token_burn", "relation": "calls", "context": "call", "confidence": "EXTRACTED", "source_file": "contract/src/cep18.rs", "source_location": "L241", "weight": 1.0}, {"source": "src_cep18_test_cep18_burn_full_balance_zeros_total_supply", "target": "src_cep18_deploy_with_supply", "relation": "calls", "context": "call", "confidence": "EXTRACTED", "source_file": "contract/src/cep18.rs", "source_location": "L250", "weight": 1.0}, {"source": "src_cep18_test_cep18_burn_full_balance_zeros_total_supply", "target": "src_cep18_cep18token_burn", "relation": "calls", "context": "call", "confidence": "EXTRACTED", "source_file": "contract/src/cep18.rs", "source_location": "L253", "weight": 1.0}], "raw_calls": [{"caller_nid": "src_cep18_cep18token_init", "callee": "caller", "is_member_call": true, "source_file": "/home/lviffy/Projects/casper/contract/src/cep18.rs", "source_location": "L43"}, {"caller_nid": "src_cep18_cep18token_init", "callee": "env", "is_member_call": true, "source_file": "/home/lviffy/Projects/casper/contract/src/cep18.rs", "source_location": "L43"}, {"caller_nid": "src_cep18_cep18token_transfer", "callee": "caller", "is_member_call": true, "source_file": "/home/lviffy/Projects/casper/contract/src/cep18.rs", "source_location": "L48"}, {"caller_nid": "src_cep18_cep18token_transfer", "callee": "env", "is_member_call": true, "source_file": "/home/lviffy/Projects/casper/contract/src/cep18.rs", "source_location": "L48"}, {"caller_nid": "src_cep18_cep18token_approve", "callee": "caller", "is_member_call": true, "source_file": "/home/lviffy/Projects/casper/contract/src/cep18.rs", "source_location": "L53"}, {"caller_nid": "src_cep18_cep18token_approve", "callee": "env", "is_member_call": true, "source_file": "/home/lviffy/Projects/casper/contract/src/cep18.rs", "source_location": "L53"}, {"caller_nid": "src_cep18_cep18token_transfer_from", "callee": "caller", "is_member_call": true, "source_file": "/home/lviffy/Projects/casper/contract/src/cep18.rs", "source_location": "L58"}, {"caller_nid": "src_cep18_cep18token_transfer_from", "callee": "env", "is_member_call": true, "source_file": "/home/lviffy/Projects/casper/contract/src/cep18.rs", "source_location": "L58"}, {"caller_nid": "src_cep18_cep18token_transfer_from", "callee": "unwrap_or", "is_member_call": true, "source_file": "/home/lviffy/Projects/casper/contract/src/cep18.rs", "source_location": "L59"}, {"caller_nid": "src_cep18_cep18token_transfer_from", "callee": "revert", "is_member_call": true, "source_file": "/home/lviffy/Projects/casper/contract/src/cep18.rs", "source_location": "L61"}, {"caller_nid": "src_cep18_cep18token_transfer_from", "callee": "env", "is_member_call": true, "source_file": "/home/lviffy/Projects/casper/contract/src/cep18.rs", "source_location": "L61"}, {"caller_nid": "src_cep18_cep18token_burn", "callee": "caller", "is_member_call": true, "source_file": "/home/lviffy/Projects/casper/contract/src/cep18.rs", "source_location": "L69"}, {"caller_nid": "src_cep18_cep18token_burn", "callee": "env", "is_member_call": true, "source_file": "/home/lviffy/Projects/casper/contract/src/cep18.rs", "source_location": "L69"}, {"caller_nid": "src_cep18_cep18token_burn", "callee": "unwrap_or", "is_member_call": true, "source_file": "/home/lviffy/Projects/casper/contract/src/cep18.rs", "source_location": "L70"}, {"caller_nid": "src_cep18_cep18token_burn", "callee": "revert", "is_member_call": true, "source_file": "/home/lviffy/Projects/casper/contract/src/cep18.rs", "source_location": "L72"}, {"caller_nid": "src_cep18_cep18token_burn", "callee": "env", "is_member_call": true, "source_file": "/home/lviffy/Projects/casper/contract/src/cep18.rs", "source_location": "L72"}, {"caller_nid": "src_cep18_cep18token_burn", "callee": "get_or_default", "is_member_call": true, "source_file": "/home/lviffy/Projects/casper/contract/src/cep18.rs", "source_location": "L75"}, {"caller_nid": "src_cep18_cep18token_burn", "callee": "emit_event", "is_member_call": true, "source_file": "/home/lviffy/Projects/casper/contract/src/cep18.rs", "source_location": "L77"}, {"caller_nid": "src_cep18_cep18token_burn", "callee": "env", "is_member_call": true, "source_file": "/home/lviffy/Projects/casper/contract/src/cep18.rs", "source_location": "L77"}, {"caller_nid": "src_cep18_cep18token_balance_of", "callee": "unwrap_or", "is_member_call": true, "source_file": "/home/lviffy/Projects/casper/contract/src/cep18.rs", "source_location": "L84"}, {"caller_nid": "src_cep18_cep18token_allowance", "callee": "unwrap_or", "is_member_call": true, "source_file": "/home/lviffy/Projects/casper/contract/src/cep18.rs", "source_location": "L88"}, {"caller_nid": "src_cep18_cep18token_total_supply", "callee": "get_or_default", "is_member_call": true, "source_file": "/home/lviffy/Projects/casper/contract/src/cep18.rs", "source_location": "L92"}, {"caller_nid": "src_cep18_cep18token_move_tokens", "callee": "unwrap_or", "is_member_call": true, "source_file": "/home/lviffy/Projects/casper/contract/src/cep18.rs", "source_location": "L98"}, {"caller_nid": "src_cep18_cep18token_move_tokens", "callee": "revert", "is_member_call": true, "source_file": "/home/lviffy/Projects/casper/contract/src/cep18.rs", "source_location": "L100"}, {"caller_nid": "src_cep18_cep18token_move_tokens", "callee": "env", "is_member_call": true, "source_file": "/home/lviffy/Projects/casper/contract/src/cep18.rs", "source_location": "L100"}, {"caller_nid": "src_cep18_cep18token_move_tokens", "callee": "unwrap_or", "is_member_call": true, "source_file": "/home/lviffy/Projects/casper/contract/src/cep18.rs", "source_location": "L102"}, {"caller_nid": "src_cep18_test_cep18_initial_supply_assigned_to_deployer", "callee": "get_account", "is_member_call": true, "source_file": "/home/lviffy/Projects/casper/contract/src/cep18.rs", "source_location": "L141"}, {"caller_nid": "src_cep18_test_cep18_transfer_moves_balance", "callee": "get_account", "is_member_call": true, "source_file": "/home/lviffy/Projects/casper/contract/src/cep18.rs", "source_location": "L149"}, {"caller_nid": "src_cep18_test_cep18_transfer_moves_balance", "callee": "get_account", "is_member_call": true, "source_file": "/home/lviffy/Projects/casper/contract/src/cep18.rs", "source_location": "L150"}, {"caller_nid": "src_cep18_test_cep18_transfer_moves_balance", "callee": "set_caller", "is_member_call": true, "source_file": "/home/lviffy/Projects/casper/contract/src/cep18.rs", "source_location": "L151"}, {"caller_nid": "src_cep18_test_cep18_transfer_reverts_on_insufficient_balance", "callee": "get_account", "is_member_call": true, "source_file": "/home/lviffy/Projects/casper/contract/src/cep18.rs", "source_location": "L161"}, {"caller_nid": "src_cep18_test_cep18_transfer_reverts_on_insufficient_balance", "callee": "set_caller", "is_member_call": true, "source_file": "/home/lviffy/Projects/casper/contract/src/cep18.rs", "source_location": "L162"}, {"caller_nid": "src_cep18_test_cep18_transfer_reverts_on_insufficient_balance", "callee": "get_account", "is_member_call": true, "source_file": "/home/lviffy/Projects/casper/contract/src/cep18.rs", "source_location": "L162"}, {"caller_nid": "src_cep18_test_cep18_approve_and_transfer_from", "callee": "get_account", "is_member_call": true, "source_file": "/home/lviffy/Projects/casper/contract/src/cep18.rs", "source_location": "L169"}, {"caller_nid": "src_cep18_test_cep18_approve_and_transfer_from", "callee": "get_account", "is_member_call": true, "source_file": "/home/lviffy/Projects/casper/contract/src/cep18.rs", "source_location": "L170"}, {"caller_nid": "src_cep18_test_cep18_approve_and_transfer_from", "callee": "get_account", "is_member_call": true, "source_file": "/home/lviffy/Projects/casper/contract/src/cep18.rs", "source_location": "L171"}, {"caller_nid": "src_cep18_test_cep18_approve_and_transfer_from", "callee": "set_caller", "is_member_call": true, "source_file": "/home/lviffy/Projects/casper/contract/src/cep18.rs", "source_location": "L172"}, {"caller_nid": "src_cep18_test_cep18_approve_and_transfer_from", "callee": "set_caller", "is_member_call": true, "source_file": "/home/lviffy/Projects/casper/contract/src/cep18.rs", "source_location": "L175"}, {"caller_nid": "src_cep18_test_cep18_transfer_from_reverts_on_insufficient_allowance", "callee": "get_account", "is_member_call": true, "source_file": "/home/lviffy/Projects/casper/contract/src/cep18.rs", "source_location": "L186"}, {"caller_nid": "src_cep18_test_cep18_transfer_from_reverts_on_insufficient_allowance", "callee": "get_account", "is_member_call": true, "source_file": "/home/lviffy/Projects/casper/contract/src/cep18.rs", "source_location": "L187"}, {"caller_nid": "src_cep18_test_cep18_transfer_from_reverts_on_insufficient_allowance", "callee": "get_account", "is_member_call": true, "source_file": "/home/lviffy/Projects/casper/contract/src/cep18.rs", "source_location": "L188"}, {"caller_nid": "src_cep18_test_cep18_transfer_from_reverts_on_insufficient_allowance", "callee": "set_caller", "is_member_call": true, "source_file": "/home/lviffy/Projects/casper/contract/src/cep18.rs", "source_location": "L189"}, {"caller_nid": "src_cep18_test_cep18_transfer_from_reverts_on_insufficient_allowance", "callee": "set_caller", "is_member_call": true, "source_file": "/home/lviffy/Projects/casper/contract/src/cep18.rs", "source_location": "L191"}, {"caller_nid": "src_cep18_test_cep18_burn_reduces_balance_and_total_supply", "callee": "get_account", "is_member_call": true, "source_file": "/home/lviffy/Projects/casper/contract/src/cep18.rs", "source_location": "L198"}, {"caller_nid": "src_cep18_test_cep18_burn_reduces_balance_and_total_supply", "callee": "set_caller", "is_member_call": true, "source_file": "/home/lviffy/Projects/casper/contract/src/cep18.rs", "source_location": "L199"}, {"caller_nid": "src_cep18_test_cep18_burn_reverts_on_insufficient_balance", "callee": "set_caller", "is_member_call": true, "source_file": "/home/lviffy/Projects/casper/contract/src/cep18.rs", "source_location": "L209"}, {"caller_nid": "src_cep18_test_cep18_burn_reverts_on_insufficient_balance", "callee": "get_account", "is_member_call": true, "source_file": "/home/lviffy/Projects/casper/contract/src/cep18.rs", "source_location": "L209"}, {"caller_nid": "src_cep18_test_cep18_burn_reverts_when_caller_has_no_balance", "callee": "get_account", "is_member_call": true, "source_file": "/home/lviffy/Projects/casper/contract/src/cep18.rs", "source_location": "L217"}, {"caller_nid": "src_cep18_test_cep18_burn_reverts_when_caller_has_no_balance", "callee": "set_caller", "is_member_call": true, "source_file": "/home/lviffy/Projects/casper/contract/src/cep18.rs", "source_location": "L218"}, {"caller_nid": "src_cep18_test_cep18_burn_only_affects_caller", "callee": "get_account", "is_member_call": true, "source_file": "/home/lviffy/Projects/casper/contract/src/cep18.rs", "source_location": "L225"}, {"caller_nid": "src_cep18_test_cep18_burn_only_affects_caller", "callee": "get_account", "is_member_call": true, "source_file": "/home/lviffy/Projects/casper/contract/src/cep18.rs", "source_location": "L226"}, {"caller_nid": "src_cep18_test_cep18_burn_only_affects_caller", "callee": "set_caller", "is_member_call": true, "source_file": "/home/lviffy/Projects/casper/contract/src/cep18.rs", "source_location": "L227"}, {"caller_nid": "src_cep18_test_cep18_burn_only_affects_caller", "callee": "set_caller", "is_member_call": true, "source_file": "/home/lviffy/Projects/casper/contract/src/cep18.rs", "source_location": "L229"}, {"caller_nid": "src_cep18_test_cep18_burn_emits_event", "callee": "get_account", "is_member_call": true, "source_file": "/home/lviffy/Projects/casper/contract/src/cep18.rs", "source_location": "L239"}, {"caller_nid": "src_cep18_test_cep18_burn_emits_event", "callee": "set_caller", "is_member_call": true, "source_file": "/home/lviffy/Projects/casper/contract/src/cep18.rs", "source_location": "L240"}, {"caller_nid": "src_cep18_test_cep18_burn_full_balance_zeros_total_supply", "callee": "get_account", "is_member_call": true, "source_file": "/home/lviffy/Projects/casper/contract/src/cep18.rs", "source_location": "L251"}, {"caller_nid": "src_cep18_test_cep18_burn_full_balance_zeros_total_supply", "callee": "set_caller", "is_member_call": true, "source_file": "/home/lviffy/Projects/casper/contract/src/cep18.rs", "source_location": "L252"}]}